mputils/__init__.py
mputils/actions.py
mputils/cli.py
mputils/multi.py
mputils/utils.py
mputils-0.1.0.dist-info/entry_points.txt
mputils-0.1.0.dist-info/WHEEL
mputils-0.1.0.dist-info/METADATA
mputils-0.1.0.dist-info/RECORD
